{
	"name": "LoL ETL",
	"properties": {
		"nbformat": 4,
		"nbformat_minor": 2,
		"sessionProperties": {
			"driverMemory": "28g",
			"driverCores": 4,
			"executorMemory": "28g",
			"executorCores": 4,
			"numExecutors": 2,
			"runAsWorkspaceSystemIdentity": false,
			"conf": {
				"spark.dynamicAllocation.enabled": "false",
				"spark.dynamicAllocation.minExecutors": "2",
				"spark.dynamicAllocation.maxExecutors": "2",
				"spark.autotune.trackingId": "77005dcd-8352-4aaf-b0b2-204164022e80"
			}
		},
		"metadata": {
			"saveOutput": true,
			"synapse_widget": {
				"version": "0.1"
			},
			"enableDebugMode": false,
			"kernelspec": {
				"name": "synapse_pyspark",
				"display_name": "python"
			},
			"language_info": {
				"name": "python"
			},
			"sessionKeepAliveTimeout": 30
		},
		"cells": [
			{
				"cell_type": "code",
				"source": [
					""
				]
			}
		]
	}
}